{
    "metrics": [
        {
            "_class_path": "fedot.core.composer.metrics/QualityMetric.get_value"
        }
    ],
    "individuals": [
        [
            {
                "uid": "20069f65-3c6c-460c-a238-58637dbfc347",
                "parent_operators": [],
                "fitness": 1022.9371864525193,
                "graph": {
                    "nodes": [
                        {
                            "_nodes_from": [
                                "a0ca511c-e2af-40a2-95c1-4fd5d73080d3"
                            ],
                            "content": {
                                "name": "ridge",
                                "params": "default_params"
                            },
                            "uid": "4c6a65de-0713-42b5-ba23-d90369f73285",
                            "rating": null,
                            "_class_path": "fedot.core.optimisers.graph/OptNode"
                        },
                        {
                            "_nodes_from": null,
                            "content": {
                                "name": "scaling",
                                "params": "default_params"
                            },
                            "uid": "a0ca511c-e2af-40a2-95c1-4fd5d73080d3",
                            "rating": null,
                            "direct_set": false,
                            "_class_path": "fedot.core.optimisers.graph/OptNode"
                        }
                    ],
                    "_class_path": "fedot.core.optimisers.graph/OptGraph"
                },
                "metadata": {
                    "computation_time": 0.3758716
                },
                "_class_path": "fedot.core.optimisers.gp_comp.individual/Individual"
            }
        ],
        [
            {
                "uid": "20069f65-3c6c-460c-a238-58637dbfc347",
                "parent_operators": [],
                "fitness": 1022.9371864525193,
                "graph": {
                    "nodes": [
                        {
                            "_nodes_from": [
                                "a0ca511c-e2af-40a2-95c1-4fd5d73080d3"
                            ],
                            "content": {
                                "name": "ridge",
                                "params": "default_params"
                            },
                            "uid": "4c6a65de-0713-42b5-ba23-d90369f73285",
                            "rating": null,
                            "_class_path": "fedot.core.optimisers.graph/OptNode"
                        },
                        {
                            "_nodes_from": null,
                            "content": {
                                "name": "scaling",
                                "params": "default_params"
                            },
                            "uid": "a0ca511c-e2af-40a2-95c1-4fd5d73080d3",
                            "rating": null,
                            "direct_set": false,
                            "_class_path": "fedot.core.optimisers.graph/OptNode"
                        }
                    ],
                    "_class_path": "fedot.core.optimisers.graph/OptGraph"
                },
                "metadata": {
                    "computation_time": 0.5031298999999994
                },
                "_class_path": "fedot.core.optimisers.gp_comp.individual/Individual"
            },
            {
                "uid": "15470ed4-2cf6-4a7d-b017-aab6bf43b8a8",
                "parent_operators": [
                    {
                        "operator_name": "<function parameter_change_mutation at 0x000001ACB7E1F790>",
                        "operator_type": "mutation",
                        "parent_individuals": [
                            "20069f65-3c6c-460c-a238-58637dbfc347"
                        ],
                        "uid": "0cb1595d-b278-4676-968b-a70563f4b714",
                        "_class_path": "fedot.core.optimisers.opt_history/ParentOperator"
                    }
                ],
                "fitness": 1022.9371864525193,
                "graph": {
                    "nodes": [
                        {
                            "_nodes_from": [
                                "4e803483-bf24-4e1d-b880-5577fdaa430c"
                            ],
                            "content": {
                                "name": "ridge",
                                "params": "default_params"
                            },
                            "uid": "64f80eed-2f68-4065-ab74-7ce7f5d09715",
                            "rating": null,
                            "_class_path": "fedot.core.optimisers.graph/OptNode"
                        },
                        {
                            "_nodes_from": null,
                            "content": {
                                "name": "scaling",
                                "params": "default_params"
                            },
                            "uid": "4e803483-bf24-4e1d-b880-5577fdaa430c",
                            "rating": null,
                            "direct_set": false,
                            "_class_path": "fedot.core.optimisers.graph/OptNode"
                        }
                    ],
                    "_class_path": "fedot.core.optimisers.graph/OptGraph"
                },
                "metadata": {
                    "computation_time": 0.4886798999999993
                },
                "_class_path": "fedot.core.optimisers.gp_comp.individual/Individual"
            },
            {
                "uid": "d6d5a009-2fc9-407f-8065-8c2a806edcb6",
                "parent_operators": [
                    {
                        "operator_name": "<function boosting_mutation at 0x000001ACB7E1F8B0>",
                        "operator_type": "mutation",
                        "parent_individuals": [
                            "20069f65-3c6c-460c-a238-58637dbfc347"
                        ],
                        "uid": "ec49dba0-ebe2-400d-aa88-c3299fe60e05",
                        "_class_path": "fedot.core.optimisers.opt_history/ParentOperator"
                    }
                ],
                "fitness": 1022.9371864525193,
                "graph": {
                    "nodes": [
                        {
                            "_nodes_from": [
                                "09b47b89-181a-4111-85e3-fa1dcf517f02"
                            ],
                            "content": {
                                "name": "ridge",
                                "params": "default_params"
                            },
                            "uid": "fe70d41a-a792-4a46-ad94-c99d36d0d442",
                            "rating": null,
                            "_class_path": "fedot.core.optimisers.graph/OptNode"
                        },
                        {
                            "_nodes_from": null,
                            "content": {
                                "name": "scaling",
                                "params": "default_params"
                            },
                            "uid": "09b47b89-181a-4111-85e3-fa1dcf517f02",
                            "rating": null,
                            "direct_set": false,
                            "_class_path": "fedot.core.optimisers.graph/OptNode"
                        }
                    ],
                    "_class_path": "fedot.core.optimisers.graph/OptGraph"
                },
                "metadata": {
                    "computation_time": 0.49301779999999873
                },
                "_class_path": "fedot.core.optimisers.gp_comp.individual/Individual"
            }
        ],
        [
            {
                "uid": "20069f65-3c6c-460c-a238-58637dbfc347",
                "parent_operators": [],
                "fitness": 1022.9371864525193,
                "graph": {
                    "nodes": [
                        {
                            "_nodes_from": [
                                "a0ca511c-e2af-40a2-95c1-4fd5d73080d3"
                            ],
                            "content": {
                                "name": "ridge",
                                "params": "default_params"
                            },
                            "uid": "4c6a65de-0713-42b5-ba23-d90369f73285",
                            "rating": null,
                            "_class_path": "fedot.core.optimisers.graph/OptNode"
                        },
                        {
                            "_nodes_from": null,
                            "content": {
                                "name": "scaling",
                                "params": "default_params"
                            },
                            "uid": "a0ca511c-e2af-40a2-95c1-4fd5d73080d3",
                            "rating": null,
                            "direct_set": false,
                            "_class_path": "fedot.core.optimisers.graph/OptNode"
                        }
                    ],
                    "_class_path": "fedot.core.optimisers.graph/OptGraph"
                },
                "metadata": {
                    "computation_time": 0.5031298999999994
                },
                "_class_path": "fedot.core.optimisers.gp_comp.individual/Individual"
            },
            {
                "uid": "15470ed4-2cf6-4a7d-b017-aab6bf43b8a8",
                "parent_operators": [
                    {
                        "operator_name": "<function parameter_change_mutation at 0x000001ACB7E1F790>",
                        "operator_type": "mutation",
                        "parent_individuals": [
                            "20069f65-3c6c-460c-a238-58637dbfc347"
                        ],
                        "uid": "0cb1595d-b278-4676-968b-a70563f4b714",
                        "_class_path": "fedot.core.optimisers.opt_history/ParentOperator"
                    }
                ],
                "fitness": 1022.9371864525193,
                "graph": {
                    "nodes": [
                        {
                            "_nodes_from": [
                                "4e803483-bf24-4e1d-b880-5577fdaa430c"
                            ],
                            "content": {
                                "name": "ridge",
                                "params": "default_params"
                            },
                            "uid": "64f80eed-2f68-4065-ab74-7ce7f5d09715",
                            "rating": null,
                            "_class_path": "fedot.core.optimisers.graph/OptNode"
                        },
                        {
                            "_nodes_from": null,
                            "content": {
                                "name": "scaling",
                                "params": "default_params"
                            },
                            "uid": "4e803483-bf24-4e1d-b880-5577fdaa430c",
                            "rating": null,
                            "direct_set": false,
                            "_class_path": "fedot.core.optimisers.graph/OptNode"
                        }
                    ],
                    "_class_path": "fedot.core.optimisers.graph/OptGraph"
                },
                "metadata": {
                    "computation_time": 0.4886798999999993
                },
                "_class_path": "fedot.core.optimisers.gp_comp.individual/Individual"
            },
            {
                "uid": "d6d5a009-2fc9-407f-8065-8c2a806edcb6",
                "parent_operators": [],
                "fitness": 1022.9371864525193,
                "graph": {
                    "nodes": [
                        {
                            "_nodes_from": [
                                "09b47b89-181a-4111-85e3-fa1dcf517f02"
                            ],
                            "content": {
                                "name": "ridge",
                                "params": "default_params"
                            },
                            "uid": "fe70d41a-a792-4a46-ad94-c99d36d0d442",
                            "rating": null,
                            "_class_path": "fedot.core.optimisers.graph/OptNode"
                        },
                        {
                            "_nodes_from": null,
                            "content": {
                                "name": "scaling",
                                "params": "default_params"
                            },
                            "uid": "09b47b89-181a-4111-85e3-fa1dcf517f02",
                            "rating": null,
                            "direct_set": false,
                            "_class_path": "fedot.core.optimisers.graph/OptNode"
                        }
                    ],
                    "_class_path": "fedot.core.optimisers.graph/OptGraph"
                },
                "metadata": {
                    "computation_time": 0.49301779999999873
                },
                "_class_path": "fedot.core.optimisers.gp_comp.individual/Individual"
            },
            {
                "uid": "0d2b5370-2474-42da-ad16-df8ee8311d3f",
                "parent_operators": [
                    {
                        "operator_name": "MutationTypesEnum.single_add",
                        "operator_type": "mutation",
                        "parent_individuals": [
                            "d6d5a009-2fc9-407f-8065-8c2a806edcb6"
                        ],
                        "uid": "2775ee66-1b6c-4741-b061-b1484a6ab1ca",
                        "_class_path": "fedot.core.optimisers.opt_history/ParentOperator"
                    }
                ],
                "fitness": 1022.9371864525193,
                "graph": {
                    "nodes": [
                        {
                            "_nodes_from": [
                                "09b47b89-181a-4111-85e3-fa1dcf517f02"
                            ],
                            "content": {
                                "name": "ridge",
                                "params": "default_params"
                            },
                            "uid": "fe70d41a-a792-4a46-ad94-c99d36d0d442",
                            "rating": null,
                            "_class_path": "fedot.core.optimisers.graph/OptNode"
                        },
                        {
                            "_nodes_from": null,
                            "content": {
                                "name": "scaling",
                                "params": "default_params"
                            },
                            "uid": "09b47b89-181a-4111-85e3-fa1dcf517f02",
                            "rating": null,
                            "direct_set": false,
                            "_class_path": "fedot.core.optimisers.graph/OptNode"
                        }
                    ],
                    "_class_path": "fedot.core.optimisers.graph/OptGraph"
                },
                "metadata": {
                    "computation_time": 0.4397473000000005
                },
                "_class_path": "fedot.core.optimisers.gp_comp.individual/Individual"
            },
            {
                "uid": "c37e6413-2d33-4920-90e3-7097ce8cb4e0",
                "parent_operators": [
                    {
                        "operator_name": "MutationTypesEnum.single_change",
                        "operator_type": "mutation",
                        "parent_individuals": [
                            "20069f65-3c6c-460c-a238-58637dbfc347"
                        ],
                        "uid": "0ef6792e-7495-4b25-87c6-e3a639c6d78e",
                        "_class_path": "fedot.core.optimisers.opt_history/ParentOperator"
                    }
                ],
                "fitness": 1022.9371864525193,
                "graph": {
                    "nodes": [
                        {
                            "_nodes_from": [
                                "a0ca511c-e2af-40a2-95c1-4fd5d73080d3"
                            ],
                            "content": {
                                "name": "ridge",
                                "params": "default_params"
                            },
                            "uid": "4c6a65de-0713-42b5-ba23-d90369f73285",
                            "rating": null,
                            "_class_path": "fedot.core.optimisers.graph/OptNode"
                        },
                        {
                            "_nodes_from": null,
                            "content": {
                                "name": "scaling",
                                "params": "default_params"
                            },
                            "uid": "a0ca511c-e2af-40a2-95c1-4fd5d73080d3",
                            "rating": null,
                            "direct_set": false,
                            "_class_path": "fedot.core.optimisers.graph/OptNode"
                        }
                    ],
                    "_class_path": "fedot.core.optimisers.graph/OptGraph"
                },
                "metadata": {
                    "computation_time": 0.4430599999999991
                },
                "_class_path": "fedot.core.optimisers.gp_comp.individual/Individual"
            }
        ],
        [
            {
                "uid": "20069f65-3c6c-460c-a238-58637dbfc347",
                "parent_operators": [],
                "fitness": 1022.9371864525193,
                "graph": {
                    "nodes": [
                        {
                            "_nodes_from": [
                                "a0ca511c-e2af-40a2-95c1-4fd5d73080d3"
                            ],
                            "content": {
                                "name": "ridge",
                                "params": "default_params"
                            },
                            "uid": "4c6a65de-0713-42b5-ba23-d90369f73285",
                            "rating": null,
                            "_class_path": "fedot.core.optimisers.graph/OptNode"
                        },
                        {
                            "_nodes_from": null,
                            "content": {
                                "name": "scaling",
                                "params": "default_params"
                            },
                            "uid": "a0ca511c-e2af-40a2-95c1-4fd5d73080d3",
                            "rating": null,
                            "direct_set": false,
                            "_class_path": "fedot.core.optimisers.graph/OptNode"
                        }
                    ],
                    "_class_path": "fedot.core.optimisers.graph/OptGraph"
                },
                "metadata": {
                    "computation_time": 0.5031298999999994
                },
                "_class_path": "fedot.core.optimisers.gp_comp.individual/Individual"
            }
        ]
    ],
    "archive_history": [
        [
            {
                "uid": "20069f65-3c6c-460c-a238-58637dbfc347",
                "parent_operators": [],
                "fitness": 1022.9371864525193,
                "graph": {
                    "nodes": [
                        {
                            "_nodes_from": [
                                "a0ca511c-e2af-40a2-95c1-4fd5d73080d3"
                            ],
                            "content": {
                                "name": "ridge",
                                "params": "default_params"
                            },
                            "uid": "4c6a65de-0713-42b5-ba23-d90369f73285",
                            "rating": null,
                            "_class_path": "fedot.core.optimisers.graph/OptNode"
                        },
                        {
                            "_nodes_from": null,
                            "content": {
                                "name": "scaling",
                                "params": "default_params"
                            },
                            "uid": "a0ca511c-e2af-40a2-95c1-4fd5d73080d3",
                            "rating": null,
                            "direct_set": false,
                            "_class_path": "fedot.core.optimisers.graph/OptNode"
                        }
                    ],
                    "_class_path": "fedot.core.optimisers.graph/OptGraph"
                },
                "metadata": {
                    "computation_time": 0.5031298999999994
                },
                "_class_path": "fedot.core.optimisers.gp_comp.individual/Individual"
            },
            {
                "uid": "15470ed4-2cf6-4a7d-b017-aab6bf43b8a8",
                "parent_operators": [
                    {
                        "operator_name": "<function parameter_change_mutation at 0x000001ACB7E1F790>",
                        "operator_type": "mutation",
                        "parent_individuals": [
                            "20069f65-3c6c-460c-a238-58637dbfc347"
                        ],
                        "uid": "0cb1595d-b278-4676-968b-a70563f4b714",
                        "_class_path": "fedot.core.optimisers.opt_history/ParentOperator"
                    }
                ],
                "fitness": 1022.9371864525193,
                "graph": {
                    "nodes": [
                        {
                            "_nodes_from": [
                                "4e803483-bf24-4e1d-b880-5577fdaa430c"
                            ],
                            "content": {
                                "name": "ridge",
                                "params": "default_params"
                            },
                            "uid": "64f80eed-2f68-4065-ab74-7ce7f5d09715",
                            "rating": null,
                            "_class_path": "fedot.core.optimisers.graph/OptNode"
                        },
                        {
                            "_nodes_from": null,
                            "content": {
                                "name": "scaling",
                                "params": "default_params"
                            },
                            "uid": "4e803483-bf24-4e1d-b880-5577fdaa430c",
                            "rating": null,
                            "direct_set": false,
                            "_class_path": "fedot.core.optimisers.graph/OptNode"
                        }
                    ],
                    "_class_path": "fedot.core.optimisers.graph/OptGraph"
                },
                "metadata": {
                    "computation_time": 0.4886798999999993
                },
                "_class_path": "fedot.core.optimisers.gp_comp.individual/Individual"
            },
            {
                "uid": "d6d5a009-2fc9-407f-8065-8c2a806edcb6",
                "parent_operators": [
                    {
                        "operator_name": "<function boosting_mutation at 0x000001ACB7E1F8B0>",
                        "operator_type": "mutation",
                        "parent_individuals": [
                            "20069f65-3c6c-460c-a238-58637dbfc347"
                        ],
                        "uid": "ec49dba0-ebe2-400d-aa88-c3299fe60e05",
                        "_class_path": "fedot.core.optimisers.opt_history/ParentOperator"
                    }
                ],
                "fitness": 1022.9371864525193,
                "graph": {
                    "nodes": [
                        {
                            "_nodes_from": [
                                "09b47b89-181a-4111-85e3-fa1dcf517f02"
                            ],
                            "content": {
                                "name": "ridge",
                                "params": "default_params"
                            },
                            "uid": "fe70d41a-a792-4a46-ad94-c99d36d0d442",
                            "rating": null,
                            "_class_path": "fedot.core.optimisers.graph/OptNode"
                        },
                        {
                            "_nodes_from": null,
                            "content": {
                                "name": "scaling",
                                "params": "default_params"
                            },
                            "uid": "09b47b89-181a-4111-85e3-fa1dcf517f02",
                            "rating": null,
                            "direct_set": false,
                            "_class_path": "fedot.core.optimisers.graph/OptNode"
                        }
                    ],
                    "_class_path": "fedot.core.optimisers.graph/OptGraph"
                },
                "metadata": {
                    "computation_time": 0.49301779999999873
                },
                "_class_path": "fedot.core.optimisers.gp_comp.individual/Individual"
            }
        ],
        [
            {
                "uid": "20069f65-3c6c-460c-a238-58637dbfc347",
                "parent_operators": [],
                "fitness": 1022.9371864525193,
                "graph": {
                    "nodes": [
                        {
                            "_nodes_from": [
                                "a0ca511c-e2af-40a2-95c1-4fd5d73080d3"
                            ],
                            "content": {
                                "name": "ridge",
                                "params": "default_params"
                            },
                            "uid": "4c6a65de-0713-42b5-ba23-d90369f73285",
                            "rating": null,
                            "_class_path": "fedot.core.optimisers.graph/OptNode"
                        },
                        {
                            "_nodes_from": null,
                            "content": {
                                "name": "scaling",
                                "params": "default_params"
                            },
                            "uid": "a0ca511c-e2af-40a2-95c1-4fd5d73080d3",
                            "rating": null,
                            "direct_set": false,
                            "_class_path": "fedot.core.optimisers.graph/OptNode"
                        }
                    ],
                    "_class_path": "fedot.core.optimisers.graph/OptGraph"
                },
                "metadata": {
                    "computation_time": 0.5031298999999994
                },
                "_class_path": "fedot.core.optimisers.gp_comp.individual/Individual"
            },
            {
                "uid": "15470ed4-2cf6-4a7d-b017-aab6bf43b8a8",
                "parent_operators": [
                    {
                        "operator_name": "<function parameter_change_mutation at 0x000001ACB7E1F790>",
                        "operator_type": "mutation",
                        "parent_individuals": [
                            "20069f65-3c6c-460c-a238-58637dbfc347"
                        ],
                        "uid": "0cb1595d-b278-4676-968b-a70563f4b714",
                        "_class_path": "fedot.core.optimisers.opt_history/ParentOperator"
                    }
                ],
                "fitness": 1022.9371864525193,
                "graph": {
                    "nodes": [
                        {
                            "_nodes_from": [
                                "4e803483-bf24-4e1d-b880-5577fdaa430c"
                            ],
                            "content": {
                                "name": "ridge",
                                "params": "default_params"
                            },
                            "uid": "64f80eed-2f68-4065-ab74-7ce7f5d09715",
                            "rating": null,
                            "_class_path": "fedot.core.optimisers.graph/OptNode"
                        },
                        {
                            "_nodes_from": null,
                            "content": {
                                "name": "scaling",
                                "params": "default_params"
                            },
                            "uid": "4e803483-bf24-4e1d-b880-5577fdaa430c",
                            "rating": null,
                            "direct_set": false,
                            "_class_path": "fedot.core.optimisers.graph/OptNode"
                        }
                    ],
                    "_class_path": "fedot.core.optimisers.graph/OptGraph"
                },
                "metadata": {
                    "computation_time": 0.4886798999999993
                },
                "_class_path": "fedot.core.optimisers.gp_comp.individual/Individual"
            },
            {
                "uid": "d6d5a009-2fc9-407f-8065-8c2a806edcb6",
                "parent_operators": [],
                "fitness": 1022.9371864525193,
                "graph": {
                    "nodes": [
                        {
                            "_nodes_from": [
                                "09b47b89-181a-4111-85e3-fa1dcf517f02"
                            ],
                            "content": {
                                "name": "ridge",
                                "params": "default_params"
                            },
                            "uid": "fe70d41a-a792-4a46-ad94-c99d36d0d442",
                            "rating": null,
                            "_class_path": "fedot.core.optimisers.graph/OptNode"
                        },
                        {
                            "_nodes_from": null,
                            "content": {
                                "name": "scaling",
                                "params": "default_params"
                            },
                            "uid": "09b47b89-181a-4111-85e3-fa1dcf517f02",
                            "rating": null,
                            "direct_set": false,
                            "_class_path": "fedot.core.optimisers.graph/OptNode"
                        }
                    ],
                    "_class_path": "fedot.core.optimisers.graph/OptGraph"
                },
                "metadata": {
                    "computation_time": 0.49301779999999873
                },
                "_class_path": "fedot.core.optimisers.gp_comp.individual/Individual"
            },
            {
                "uid": "20069f65-3c6c-460c-a238-58637dbfc347",
                "parent_operators": [],
                "fitness": 1022.9371864525193,
                "graph": {
                    "nodes": [
                        {
                            "_nodes_from": [
                                "a0ca511c-e2af-40a2-95c1-4fd5d73080d3"
                            ],
                            "content": {
                                "name": "ridge",
                                "params": "default_params"
                            },
                            "uid": "4c6a65de-0713-42b5-ba23-d90369f73285",
                            "rating": null,
                            "_class_path": "fedot.core.optimisers.graph/OptNode"
                        },
                        {
                            "_nodes_from": null,
                            "content": {
                                "name": "scaling",
                                "params": "default_params"
                            },
                            "uid": "a0ca511c-e2af-40a2-95c1-4fd5d73080d3",
                            "rating": null,
                            "direct_set": false,
                            "_class_path": "fedot.core.optimisers.graph/OptNode"
                        }
                    ],
                    "_class_path": "fedot.core.optimisers.graph/OptGraph"
                },
                "metadata": {
                    "computation_time": 0.5031298999999994
                },
                "_class_path": "fedot.core.optimisers.gp_comp.individual/Individual"
            },
            {
                "uid": "15470ed4-2cf6-4a7d-b017-aab6bf43b8a8",
                "parent_operators": [
                    {
                        "operator_name": "<function parameter_change_mutation at 0x000001ACB7E1F790>",
                        "operator_type": "mutation",
                        "parent_individuals": [
                            "20069f65-3c6c-460c-a238-58637dbfc347"
                        ],
                        "uid": "0cb1595d-b278-4676-968b-a70563f4b714",
                        "_class_path": "fedot.core.optimisers.opt_history/ParentOperator"
                    }
                ],
                "fitness": 1022.9371864525193,
                "graph": {
                    "nodes": [
                        {
                            "_nodes_from": [
                                "4e803483-bf24-4e1d-b880-5577fdaa430c"
                            ],
                            "content": {
                                "name": "ridge",
                                "params": "default_params"
                            },
                            "uid": "64f80eed-2f68-4065-ab74-7ce7f5d09715",
                            "rating": null,
                            "_class_path": "fedot.core.optimisers.graph/OptNode"
                        },
                        {
                            "_nodes_from": null,
                            "content": {
                                "name": "scaling",
                                "params": "default_params"
                            },
                            "uid": "4e803483-bf24-4e1d-b880-5577fdaa430c",
                            "rating": null,
                            "direct_set": false,
                            "_class_path": "fedot.core.optimisers.graph/OptNode"
                        }
                    ],
                    "_class_path": "fedot.core.optimisers.graph/OptGraph"
                },
                "metadata": {
                    "computation_time": 0.4886798999999993
                },
                "_class_path": "fedot.core.optimisers.gp_comp.individual/Individual"
            },
            {
                "uid": "d6d5a009-2fc9-407f-8065-8c2a806edcb6",
                "parent_operators": [],
                "fitness": 1022.9371864525193,
                "graph": {
                    "nodes": [
                        {
                            "_nodes_from": [
                                "09b47b89-181a-4111-85e3-fa1dcf517f02"
                            ],
                            "content": {
                                "name": "ridge",
                                "params": "default_params"
                            },
                            "uid": "fe70d41a-a792-4a46-ad94-c99d36d0d442",
                            "rating": null,
                            "_class_path": "fedot.core.optimisers.graph/OptNode"
                        },
                        {
                            "_nodes_from": null,
                            "content": {
                                "name": "scaling",
                                "params": "default_params"
                            },
                            "uid": "09b47b89-181a-4111-85e3-fa1dcf517f02",
                            "rating": null,
                            "direct_set": false,
                            "_class_path": "fedot.core.optimisers.graph/OptNode"
                        }
                    ],
                    "_class_path": "fedot.core.optimisers.graph/OptGraph"
                },
                "metadata": {
                    "computation_time": 0.49301779999999873
                },
                "_class_path": "fedot.core.optimisers.gp_comp.individual/Individual"
            },
            {
                "uid": "0d2b5370-2474-42da-ad16-df8ee8311d3f",
                "parent_operators": [
                    {
                        "operator_name": "MutationTypesEnum.single_add",
                        "operator_type": "mutation",
                        "parent_individuals": [
                            "d6d5a009-2fc9-407f-8065-8c2a806edcb6"
                        ],
                        "uid": "2775ee66-1b6c-4741-b061-b1484a6ab1ca",
                        "_class_path": "fedot.core.optimisers.opt_history/ParentOperator"
                    }
                ],
                "fitness": 1022.9371864525193,
                "graph": {
                    "nodes": [
                        {
                            "_nodes_from": [
                                "09b47b89-181a-4111-85e3-fa1dcf517f02"
                            ],
                            "content": {
                                "name": "ridge",
                                "params": "default_params"
                            },
                            "uid": "fe70d41a-a792-4a46-ad94-c99d36d0d442",
                            "rating": null,
                            "_class_path": "fedot.core.optimisers.graph/OptNode"
                        },
                        {
                            "_nodes_from": null,
                            "content": {
                                "name": "scaling",
                                "params": "default_params"
                            },
                            "uid": "09b47b89-181a-4111-85e3-fa1dcf517f02",
                            "rating": null,
                            "direct_set": false,
                            "_class_path": "fedot.core.optimisers.graph/OptNode"
                        }
                    ],
                    "_class_path": "fedot.core.optimisers.graph/OptGraph"
                },
                "metadata": {
                    "computation_time": 0.4397473000000005
                },
                "_class_path": "fedot.core.optimisers.gp_comp.individual/Individual"
            },
            {
                "uid": "c37e6413-2d33-4920-90e3-7097ce8cb4e0",
                "parent_operators": [
                    {
                        "operator_name": "MutationTypesEnum.single_change",
                        "operator_type": "mutation",
                        "parent_individuals": [
                            "20069f65-3c6c-460c-a238-58637dbfc347"
                        ],
                        "uid": "0ef6792e-7495-4b25-87c6-e3a639c6d78e",
                        "_class_path": "fedot.core.optimisers.opt_history/ParentOperator"
                    }
                ],
                "fitness": 1022.9371864525193,
                "graph": {
                    "nodes": [
                        {
                            "_nodes_from": [
                                "a0ca511c-e2af-40a2-95c1-4fd5d73080d3"
                            ],
                            "content": {
                                "name": "ridge",
                                "params": "default_params"
                            },
                            "uid": "4c6a65de-0713-42b5-ba23-d90369f73285",
                            "rating": null,
                            "_class_path": "fedot.core.optimisers.graph/OptNode"
                        },
                        {
                            "_nodes_from": null,
                            "content": {
                                "name": "scaling",
                                "params": "default_params"
                            },
                            "uid": "a0ca511c-e2af-40a2-95c1-4fd5d73080d3",
                            "rating": null,
                            "direct_set": false,
                            "_class_path": "fedot.core.optimisers.graph/OptNode"
                        }
                    ],
                    "_class_path": "fedot.core.optimisers.graph/OptGraph"
                },
                "metadata": {
                    "computation_time": 0.4430599999999991
                },
                "_class_path": "fedot.core.optimisers.gp_comp.individual/Individual"
            }
        ]
    ],
    "save_folder": null,
    "_class_path": "fedot.core.optimisers.opt_history/OptHistory"
}